enviparse/__init__.py
enviparse/enviparse.py
enviparse/errors.py
enviparse/opyoid.py
enviparse-2.0.1.dist-info/LICENSE.txt
enviparse-2.0.1.dist-info/METADATA
enviparse-2.0.1.dist-info/WHEEL
enviparse-2.0.1.dist-info/top_level.txt
enviparse-2.0.1.dist-info/RECORD
